pcs_scraper/__init__.py
pcs_scraper/base.py
pcs_scraper/scrap_race.py
pcs_scraper/scrap_teams.py
pcs_utils-0.0.10.dist-info/LICENSE
pcs_utils-0.0.10.dist-info/METADATA
pcs_utils-0.0.10.dist-info/WHEEL
pcs_utils-0.0.10.dist-info/top_level.txt
pcs_utils-0.0.10.dist-info/RECORD
