Metadata-Version: 2.1
Name: pcs-utils
Version: 0.0.10
Summary: Some utils for scraping the PCS web
Home-page: https://github.com/ibairos/pcs-utils
Author: Ibai Ros
Author-email: ibai.ros@hotmail.com
Project-URL: Bug Tracker, https://github.com/ibairos/pcs-utils/issues
Classifier: Programming Language :: Python :: 3
Classifier: License :: OSI Approved :: Apache Software License
Classifier: Operating System :: OS Independent
Requires-Python: >=3.6
License-File: LICENSE
